wefe/__init__.py
wefe/_version.py
wefe/preprocessing.py
wefe/query.py
wefe/utils.py
wefe/word_embedding_model.py
wefe/datasets/__init__.py
wefe/datasets/datasets.py
wefe/datasets/data/WEAT.json
wefe/datasets/data/negative-words.txt
wefe/datasets/data/positive-words.txt
wefe/datasets/data/references.txt
wefe/datasets/data/test_model.kv
wefe/datasets/data/weat_w2v____old.txt
wefe/debias/__init__.py
wefe/debias/base_debias.py
wefe/debias/double_hard_debias.py
wefe/debias/half_sibling_regression.py
wefe/debias/hard_debias.py
wefe/debias/multiclass_hard_debias.py
wefe/debias/repulsion_attraction_neutralization.py
wefe/metrics/ECT.py
wefe/metrics/MAC.py
wefe/metrics/RIPA.py
wefe/metrics/RND.py
wefe/metrics/RNSB.py
wefe/metrics/WEAT.py
wefe/metrics/__init__.py
wefe/metrics/base_metric.py
wefe/metrics/example_metric.py
wefe-1.0.0.dist-info/licenses/LICENSE
wefe-1.0.0.dist-info/METADATA
wefe-1.0.0.dist-info/WHEEL
wefe-1.0.0.dist-info/top_level.txt
wefe-1.0.0.dist-info/RECORD
