Metadata-Version: 2.4
Name: wefe
Version: 1.0.0
Summary: The Word Embedding Fairness Evaluation Framework
Author-email: Pablo Badilla <pablo.badilla@ug.uchile.cl>, Felipe Bravo <fbravo@dcc.uchile.cl>, WEFE Team <fbravo@dcc.uchile.cl>
Maintainer-email: WEFE Team <fbravo@dcc.uchile.cl>
License-Expression: MIT
Project-URL: Homepage, https://github.com/dccuchile/wefe
Project-URL: Documentation, https://wefe.readthedocs.io/
Project-URL: Repository, https://github.com/dccuchile/wefe
Project-URL: Bug Tracker, https://github.com/dccuchile/wefe/issues
Keywords: bias,fairness,nlp,word embeddings,machine learning,artificial intelligence
Classifier: Intended Audience :: Science/Research
Classifier: Intended Audience :: Developers
Classifier: Programming Language :: Python
Classifier: Programming Language :: Python :: 3
Classifier: Programming Language :: Python :: 3.10
Classifier: Programming Language :: Python :: 3.11
Classifier: Programming Language :: Python :: 3.12
Classifier: Topic :: Software Development
Classifier: Topic :: Scientific/Engineering
Classifier: Topic :: Scientific/Engineering :: Artificial Intelligence
Classifier: Operating System :: Microsoft :: Windows
Classifier: Operating System :: POSIX
Classifier: Operating System :: Unix
Classifier: Operating System :: MacOS
Requires-Python: >=3.10
License-File: LICENSE
Requires-Dist: gensim>=3.8.3
Requires-Dist: numpy<=1.26.4
Requires-Dist: pandas>=2.0.0
Requires-Dist: plotly>=6.0.0
Requires-Dist: requests>=2.22.0
Requires-Dist: scikit-learn>=1.5.0
Requires-Dist: scipy<1.13
Requires-Dist: semantic_version>=2.8.0
Requires-Dist: tqdm>=4.0.0
Provides-Extra: pytorch
Requires-Dist: torch>=2.1.0; extra == "pytorch"
Provides-Extra: dev
Requires-Dist: docutils>=0.21.2; extra == "dev"
Requires-Dist: ipython>=8.25.0; extra == "dev"
Requires-Dist: mypy>=1.17.0; extra == "dev"
Requires-Dist: numpydoc>=1.9.0; extra == "dev"
Requires-Dist: pytest>=8.4.1; extra == "dev"
Requires-Dist: pytest-cov>=6.2.1; extra == "dev"
Requires-Dist: ruff>=0.12.3; extra == "dev"
Requires-Dist: Sphinx>=8.1.0; extra == "dev"
Requires-Dist: sphinx-copybutton>=0.5.2; extra == "dev"
Requires-Dist: sphinx-gallery>=0.19.0; extra == "dev"
Requires-Dist: sphinx-rtd-theme>=3.0.2; extra == "dev"
Requires-Dist: torch>=2.1.0; extra == "dev"
Requires-Dist: urllib3>=2.5.0; extra == "dev"
Dynamic: license-file
